{"gettingstarted_basicprojectsetup.md":"81a784b6","architecture.md":"433573e9","faq.md":"8f2cb47d","specification_basecollection.md":"9d1698af","specification_basenft.md":"bf6102cf","specification_tip4_5.md":"ab13c66c","readme.md":"5de956bf","specification_tip4_6.md":"9bc8e457","specification_tip6.md":"2668b162","specification_tip4_royalty.md":"2acbdba7","src_pages_gettingstarted_helperscripts.md":"df01390d","gettingstarted_lockliftconfigsetting.md":"aa45633d","apireferences.md":"13e0519e","specification_toc.md":"f09e2f35","specification_tip4_3.md":"1030b8ea","gettingstarted_toc.md":"e2376e07","index.md":"37b96fb2","usageanddeployment_transferringnft.md":"d26cd352","gettingstarted_deployaccount.md":"ab0b6445","specification_tip4_4.md":"92c2e0bc","src_pages_usageanddeployment_upgradeablenft.md":"86d96892","usageanddeployment_prerequisites.md":"f0f74ed1","specification_tip4_2.md":"80c5b3ac","usageanddeployment_findingnftbyindexes.md":"29d23875","specification_tip4_1.md":"a67f5244","usageanddeployment_toc.md":"401c8730","usageanddeployment_burningnft.md":"7dbe8802","usageanddeployment_mintingnft.md":"15b85ab5","usageanddeployment_deployingcollection.md":"42defd25"}
